upscale_x4/__init__.py
upscale_x4/models/FSRCNN_x2.pb
upscale_x4/models/FSRCNN_x4.pb
upscale_x4/models/__init__.py
upscale_x4-0.0.5.dist-info/LICENSE
upscale_x4-0.0.5.dist-info/METADATA
upscale_x4-0.0.5.dist-info/WHEEL
upscale_x4-0.0.5.dist-info/top_level.txt
upscale_x4-0.0.5.dist-info/RECORD
