Metadata-Version: 2.1
Name: upscale_x4
Version: 0.0.5
Summary: Upscale images or gifs by 4
Author-email: Raziel619 <raziel619dev@gmail.com>
License: MIT License
Project-URL: Homepage, https://github.com/Raziel619/upscale_x4
Keywords: AI,upscale
Classifier: License :: OSI Approved :: MIT License
Classifier: Programming Language :: Python
Classifier: Programming Language :: Python :: 3
Requires-Python: >=3.9
License-File: LICENSE
Requires-Dist: imageio
Requires-Dist: numpy
Requires-Dist: opencv-contrib-python==4.10.0.84
Requires-Dist: pillow
